guv_calcs/__init__.py
guv_calcs/_data.py
guv_calcs/_read.py
guv_calcs/_version.py
guv_calcs/calc_manager.py
guv_calcs/calc_zone.py
guv_calcs/calc_zone_new.py
guv_calcs/disinfection_calculator.py
guv_calcs/io.py
guv_calcs/lamp.py
guv_calcs/lamp_helpers.py
guv_calcs/lamp_orientation.py
guv_calcs/lamp_plotter.py
guv_calcs/lamp_surface.py
guv_calcs/reflectance.py
guv_calcs/room.py
guv_calcs/room_dims.py
guv_calcs/room_plotter.py
guv_calcs/scene.py
guv_calcs/spectrum.py
guv_calcs/trigonometry.py
guv_calcs/units.py
guv_calcs/data/UV Spectral Weighting Curves.csv
guv_calcs/data/UVC Inactivation Constants.csv
guv_calcs/data/__init__.py
guv_calcs/data/disinfection_table.csv
guv_calcs/data/__pycache__/__init__.cpython-310.pyc
guv_calcs/data/__pycache__/__init__.cpython-312.pyc
guv_calcs/data/lamp_data/B1 module.ies
guv_calcs/data/lamp_data/__init__.py
guv_calcs/data/lamp_data/aerolamp.csv
guv_calcs/data/lamp_data/aerolamp.ies
guv_calcs/data/lamp_data/beacon.csv
guv_calcs/data/lamp_data/beacon.ies
guv_calcs/data/lamp_data/lumenizer_zone.csv
guv_calcs/data/lamp_data/lumenizer_zone.ies
guv_calcs/data/lamp_data/nukit_lantern.csv
guv_calcs/data/lamp_data/nukit_lantern.ies
guv_calcs/data/lamp_data/nukit_torch.csv
guv_calcs/data/lamp_data/nukit_torch.ies
guv_calcs/data/lamp_data/sterilray.csv
guv_calcs/data/lamp_data/sterilray.ies
guv_calcs/data/lamp_data/ushio_b1.5.csv
guv_calcs/data/lamp_data/ushio_b1.5.ies
guv_calcs/data/lamp_data/ushio_b1.csv
guv_calcs/data/lamp_data/ushio_b1.ies
guv_calcs/data/lamp_data/uvpro222_b1.csv
guv_calcs/data/lamp_data/uvpro222_b1.ies
guv_calcs/data/lamp_data/uvpro222_b2.csv
guv_calcs/data/lamp_data/uvpro222_b2.ies
guv_calcs/data/lamp_data/visium.csv
guv_calcs/data/lamp_data/visium.ies
guv_calcs-0.4.30.dist-info/LICENSE
guv_calcs-0.4.30.dist-info/METADATA
guv_calcs-0.4.30.dist-info/WHEEL
guv_calcs-0.4.30.dist-info/top_level.txt
guv_calcs-0.4.30.dist-info/zip-safe
guv_calcs-0.4.30.dist-info/RECORD
